Simple-CLI/__init__.py
Simple-CLI/menu.py
simple_cli/__init__.py
simple_cli/menu.py
Simple_CLI-0.0.3.dist-info/LICENSE
Simple_CLI-0.0.3.dist-info/METADATA
Simple_CLI-0.0.3.dist-info/WHEEL
Simple_CLI-0.0.3.dist-info/top_level.txt
Simple_CLI-0.0.3.dist-info/RECORD
