Metadata-Version: 2.1
Name: Simple-CLI
Version: 0.0.3
Summary: Python CLI Library
Home-page: https://github.com/alexmanning9904/simple-cli/
Author: Alex Manning
Author-email: alex.manning9904@gmail.com
License: UNKNOWN
Platform: UNKNOWN
Classifier: Programming Language :: Python :: 3
Classifier: License :: OSI Approved :: MIT License
Classifier: Operating System :: OS Independent
